AUTHORS
ChangeLog
LICENSE
MANIFEST.in
README.md
setup.cfg
setup.py
bareon/__init__.py
bareon/errors.py
bareon/hooks.py
bareon/version.py
bareon.egg-info/PKG-INFO
bareon.egg-info/SOURCES.txt
bareon.egg-info/dependency_links.txt
bareon.egg-info/entry_points.txt
bareon.egg-info/not-zip-safe
bareon.egg-info/pbr.json
bareon.egg-info/requires.txt
bareon.egg-info/top_level.txt
bareon/actions/__init__.py
bareon/actions/base.py
bareon/cmd/__init__.py
bareon/cmd/agent.py
bareon/cmd/ironic_callback.py
bareon/drivers/__init__.py
bareon/drivers/data/__init__.py
bareon/drivers/data/base.py
bareon/drivers/data/bootstrap.py
bareon/drivers/data/generic.py
bareon/drivers/data/ironic.py
bareon/drivers/data/ks_spaces_validator.py
bareon/drivers/data/nailgun.py
bareon/drivers/data/simple.py
bareon/drivers/data/json_schemes/__init__.py
bareon/drivers/data/json_schemes/ironic.json
bareon/drivers/data/json_schemes/nailgun.json
bareon/drivers/deploy/__init__.py
bareon/drivers/deploy/base.py
bareon/drivers/deploy/flow.py
bareon/drivers/deploy/generic.py
bareon/drivers/deploy/mixins.py
bareon/drivers/deploy/nailgun.py
bareon/drivers/deploy/rsync.py
bareon/drivers/deploy/swift.py
bareon/objects/__init__.py
bareon/objects/base.py
bareon/objects/bootloader.py
bareon/objects/configdrive.py
bareon/objects/device.py
bareon/objects/image.py
bareon/objects/operating_system.py
bareon/objects/repo.py
bareon/objects/partition/__init__.py
bareon/objects/partition/fs.py
bareon/objects/partition/lv.py
bareon/objects/partition/md.py
bareon/objects/partition/parted.py
bareon/objects/partition/pv.py
bareon/objects/partition/scheme.py
bareon/objects/partition/vg.py
bareon/openstack/__init__.py
bareon/openstack/common/__init__.py
bareon/openstack/common/gettextutils.py
bareon/openstack/common/importutils.py
bareon/openstack/common/local.py
bareon/openstack/common/log.py
bareon/tests/__init__.py
bareon/tests/base.py
bareon/tests/test_artifact_utils.py
bareon/tests/test_build_utils.py
bareon/tests/test_configdrive.py
bareon/tests/test_flow_driver.py
bareon/tests/test_fs_utils.py
bareon/tests/test_generic_data_driver.py
bareon/tests/test_generic_deploy_driver.py
bareon/tests/test_grub_utils.py
bareon/tests/test_hardware_utils.py
