Metadata-Version: 1.1
Name: bareon
Version: 0.0.1a3
Summary: Bareon
Home-page: UNKNOWN
Author: Mirantis
Author-email: openstack-dev@lists.openstack.org
License: UNKNOWN
Platform: UNKNOWN
Classifier: Development Status :: 4 - Beta
Classifier: Programming Language :: Python
